[
    {
        "Muda": "17:30",
        "Nchi": "Argentina",
        "Ligi": "Primera B",
        "Mechi": "Laferrere – Dock Sud",
        "Utabiri": "under 3.5",
        "Odds": "1.20",
        "Source": "Tipsbet.co.uk"
    },
    {
        "Muda": "19:00",
        "Nchi": "Brazil",
        "Ligi": "Serie B",
        "Mechi": "CRB – Sao Bernardo",
        "Utabiri": "1x",
        "Odds": "1.20",
        "Source": "Tipsbet.co.uk"
    },
    {
        "Muda": "15:00",
        "Nchi": "Czech R.",
        "Ligi": "4.Liga",
        "Mechi": "T. Prague – Sokolov",
        "Utabiri": "1",
        "Odds": "1.69",
        "Source": "Tipsbet.co.uk"
    },
    {
        "Muda": "16:00",
        "Nchi": "Italy",
        "Ligi": "Serie C",
        "Mechi": "Ascoli – Brescia",
        "Utabiri": "1x",
        "Odds": "1.21",
        "Source": "Tipsbet.co.uk"
    },
    {
        "Muda": "15:00",
        "Nchi": "Norway",
        "Ligi": "OBOS ligaen",
        "Mechi": "Ranheim – Strommen",
        "Utabiri": "1",
        "Odds": "1.40",
        "Source": "Tipsbet.co.uk"
    },
    {
        "Muda": "19:00",
        "Nchi": "Spain",
        "Ligi": "LaLiga 2",
        "Mechi": "Las Palmas – Malaga",
        "Utabiri": "under 3.5",
        "Odds": "1.25",
        "Source": "Tipsbet.co.uk"
    },
    {
        "Muda": "13:00",
        "Nchi": "World",
        "Ligi": "Friendly I.",
        "Mechi": "Liechtenstein – Cyprus",
        "Utabiri": "2",
        "Odds": "1.37",
        "Source": "Tipsbet.co.uk"
    },
    {
        "Muda": "16:30",
        "Nchi": "World",
        "Ligi": "Friendly I.",
        "Mechi": "Denmark – Ukraine",
        "Utabiri": "1",
        "Odds": "1.66",
        "Source": "Tipsbet.co.uk"
    },
    {
        "Muda": "13:00",
        "Nchi": "France",
        "Ligi": "ATP – F. Open",
        "Mechi": "Cobolli F. – Zverev A.",
        "Utabiri": "2",
        "Odds": "1.25",
        "Source": "Tipsbet.co.uk"
    }
]